CHANGELOG.rst
MANIFEST.in
README.md
rpcdoc
rpcgencode
rpcsh
setup.cfg
setup.py
reflectrpc/__init__.py
reflectrpc/client.py
reflectrpc/cmdline.py
reflectrpc/rpcsh.py
reflectrpc/server.py
reflectrpc/simpleserver.py
reflectrpc/testing.py
reflectrpc/twistedserver.py
reflectrpc.egg-info/PKG-INFO
reflectrpc.egg-info/SOURCES.txt
reflectrpc.egg-info/dependency_links.txt
reflectrpc.egg-info/requires.txt
reflectrpc.egg-info/top_level.txt