Metadata-Version: 1.1
Name: reflectrpc
Version: 0.7.6
Summary: Self-describing JSON-RPC services made easy
Home-page: https://github.com/aheck/reflectrpc
Author: Andreas Heck
Author-email: aheck@gmx.de
License: MIT
Download-URL: https://github.com/aheck/reflectrpc/archive/v0.7.6.tar.gz
Keywords: json-rpc jsonrpc rpc webservice
Platform: UNKNOWN
Classifier: Development Status :: 4 - Beta
Classifier: Intended Audience :: Developers
Classifier: License :: OSI Approved :: MIT License
Classifier: Programming Language :: Python :: 2.7
Classifier: Programming Language :: Python :: 3.3
Classifier: Programming Language :: Python :: 3.4
Classifier: Programming Language :: Python :: 3.5
